mbipy/.DS_Store
mbipy/__init__.py
mbipy/__main__.py
mbipy/gui.py
mbipy/load.py
mbipy/orthogonal_transforms.py
mbipy/normal_integration/__init__.py
mbipy/normal_integration/padding.py
mbipy/phase_retrieval/__init__.py
mbipy/src/.DS_Store
mbipy/src/__init__.py
mbipy/src/config.py
mbipy/src/load.py
mbipy/src/orthogonal_transforms.py
mbipy/src/utils.py
mbipy/src/utils_overloads.py
mbipy/src/normal_integration/__init__.py
mbipy/src/normal_integration/overloads.py
mbipy/src/normal_integration/utils.py
mbipy/src/normal_integration/fourier/__init__.py
mbipy/src/normal_integration/fourier/arnison.py
mbipy/src/normal_integration/fourier/dct.py
mbipy/src/normal_integration/fourier/dst.py
mbipy/src/normal_integration/fourier/frankot.py
mbipy/src/normal_integration/fourier/kottler.py
mbipy/src/normal_integration/fourier/overloads.py
mbipy/src/normal_integration/fourier/padding.py
mbipy/src/normal_integration/fourier/utils.py
mbipy/src/normal_integration/least_squares/__init__.py
mbipy/src/normal_integration/least_squares/li.py
mbipy/src/normal_integration/least_squares/southwell.py
mbipy/src/normal_integration/least_squares/utils.py
mbipy/src/phase_retrieval/__init__.py
mbipy/src/phase_retrieval/utils.py
mbipy/src/phase_retrieval/explicit/__init__.py
mbipy/src/phase_retrieval/explicit/config.py
mbipy/src/phase_retrieval/explicit/umpa.py
mbipy/src/phase_retrieval/explicit/utils.py
mbipy/src/phase_retrieval/explicit/xst.py
mbipy/src/phase_retrieval/implicit/__init__.py
mbipy/src/phase_retrieval/implicit/lcs.py
mbipy/src/phase_retrieval/implicit/lcs_overload.py
mbipy/src/phase_retrieval/implicit/mist.py
mbipy/src/phase_retrieval/implicit/optical_flow.py
mbipy/src/phase_retrieval/implicit/utils.py
mbipy-0.1.0.dist-info/entry_points.txt
mbipy-0.1.0.dist-info/licenses/LICENSE
mbipy-0.1.0.dist-info/WHEEL
mbipy-0.1.0.dist-info/METADATA
mbipy-0.1.0.dist-info/RECORD
