Metadata-Version: 2.4
Name: mbipy
Version: 0.1.0
Summary: Modulation-based x-ray phase contrast imaging.
Author-email: Chris Ninham <christopher.ninham@insa-lyon.fr>
License-File: LICENSE
Requires-Dist: array-api-compat
Requires-Dist: numpy>=1.21
Requires-Dist: cupy ; extra == "cupy"
Requires-Dist: pyvkfft ; extra == "cupy"
Requires-Dist: jax ; extra == "jax"
Requires-Dist: jaxwt ; extra == "jax"
Requires-Dist: numba ; extra == "numba"
Requires-Dist: rocket-fft ; extra == "numba"
Requires-Dist: pywavelets ; extra == "numpy"
Requires-Dist: scipy ; extra == "numpy"
Requires-Dist: array-api-strict ; extra == "strict"
Requires-Dist: pytest ; extra == "test"
Requires-Dist: pytest-cov ; extra == "test"
Requires-Dist: pytest-env ; extra == "test"
Requires-Dist: pytest-randomly ; extra == "test"
Requires-Dist: torch>=1.13 ; extra == "torch"
Requires-Dist: torch-dct ; extra == "torch"
Requires-Dist: ptwt ; extra == "torch"
Project-URL: Bug Tracker, https://github.com/Nin17/mbipy/issues
Project-URL: Homepage, https://github.com/Nin17/mbipy
Provides-Extra: cupy
Provides-Extra: jax
Provides-Extra: numba
Provides-Extra: numpy
Provides-Extra: strict
Provides-Extra: test
Provides-Extra: torch
